{
    "title": "Columbia Glacier",
    "template": "location.jade",
    "blurb": "The Columbia Glacier is located in Prince William Sound, outside of Valdez, Alaska.",
    "tiles": [
    {
        "name": "Overview",
        "url": "overview.html",
        "filename": "LeWinter_Columbia_landscape-Thumbnail.jpg"
    },
    {
        "name": "Images",
        "url": "images.html",
        "filename": "_LDR0105-Thumbnail.JPG"
    },
    {
        "name": "Real-time Data",
        "url": "data.html",
        "filename": "chart.png"
    },
    {
        "name": "Time-lapse",
        "url": "timelapse.html",
        "filename": "ColumbiaIridium-Thumbnail.jpg"
    }

    ]
}
